OpenQueue/__init__.py
OpenQueue-0.0.0.dist-info/LICENSE
OpenQueue-0.0.0.dist-info/METADATA
OpenQueue-0.0.0.dist-info/WHEEL
OpenQueue-0.0.0.dist-info/top_level.txt
OpenQueue-0.0.0.dist-info/RECORD
