Metadata-Version: 2.1
Name: OpenQueue
Version: 0.0.0
Summary: OpenQueue is open-source CS: GO Tournament & PUG platform.
Home-page: https://github.com/OpenQueueCS
Author: WardPearce
Author-email: wardpearce@protonmail.com
License: GPL v3
Platform: UNKNOWN
Requires-Python: >=3.6
Requires-Dist: asyncpg (>=0.20.0)
Requires-Dist: aiomysql (>=0.0.20)
Requires-Dist: aiosqlite (>=0.13.0)
Requires-Dist: databases (>=0.2.6)
Requires-Dist: sqlalchemy (>=1.3.13)
Requires-Dist: discord.py (>=1.1.0)
Requires-Dist: alembic (>=1.4.2)
Requires-Dist: pymysql (>=0.9.3)
Requires-Dist: psycopg2 (>=2.8.5)
Requires-Dist: cryptography (>=2.9.2)
Requires-Dist: aiob2 (>=1.0.4)
Requires-Dist: aiobotocore (>=1.0.7)
Requires-Dist: aioquery (>=0.1.0)
